ripe/stat/cli/__init__.py
ripe/stat/cli/command.py
ripe/stat/cli/filters.py
ripe/stat/cli/formatters.py
ripe/stat/cli/logging.py
ripe/stat/cli/templates/abuse-contact-finder/spec.json
ripe/stat/cli/templates/abuse-contact-finder/template.jinja
ripe/stat/cli/templates/address-space-hierarchy/spec.json
ripe/stat/cli/templates/address-space-hierarchy/template.jinja
ripe/stat/cli/templates/atlas-probes/spec.json
ripe/stat/cli/templates/atlas-probes/template.jinja
ripe/stat/cli/templates/maxmind-geo-lite/spec.json
ripe/stat/cli/templates/maxmind-geo-lite/template.jinja
ripe/stat/cli/tests/data/abuse-contact-finder.json
ripe/stat/cli/tests/data/address-space-hierarchy.json
ripe/stat/cli/tests/data/atlas-probes.json
ripe/stat/cli/tests/data/maxmind-geo-lite.json
ripe/stat/cli/tests/test_abuse_contact_finder.py
ripe.stat.cli-0.1.0.dist-info/entry_points.txt
ripe.stat.cli-0.1.0.dist-info/LICENSE
ripe.stat.cli-0.1.0.dist-info/WHEEL
ripe.stat.cli-0.1.0.dist-info/METADATA
ripe.stat.cli-0.1.0.dist-info/RECORD
