Metadata-Version: 2.1
Name: ripe.stat.cli
Version: 0.1.0
Summary: A CLI for RIPEStat
Home-page: https://gitlab.com/danielquinn/ripestat-cli
License: AGPL
Author: Daniel Quinn
Author-email: code@danielquinn.org
Requires-Python: >=3.8,<4.0
Classifier: License :: Other/Proprietary License
Classifier: Programming Language :: Python :: 3
Classifier: Programming Language :: Python :: 3.10
Classifier: Programming Language :: Python :: 3.8
Classifier: Programming Language :: Python :: 3.9
Requires-Dist: Jinja2 (>=3.1.2,<4.0.0)
Requires-Dist: argcomplete (>=2.0.0,<3.0.0)
Requires-Dist: colorama (>=0.4.4,<0.5.0)
Requires-Dist: requests (>=2.27.1,<3.0.0)
Requires-Dist: tabulate (>=0.8.9,<0.9.0)
Project-URL: Documentation, https://gitlab.com/danielquinn/ripestat-cli
Project-URL: Repository, https://gitlab.com/danielquinn/ripestat-cli
